{
  "version": "25.09",
  "src": {
    "type": "n4l-sst-native",
    "ipmt": "",
    "positions": {
      "nodes": null,
      "edges": null
    }
  },
  "nodes": [
    {
      "id": 1,
      "name": "-:: _sequence_ ::          // ending sequence mode",
      "alias": "",
      "type": "Event"
    },
    {
      "id": 2,
      "name": "And everywhere that Mary went",
      "alias": "",
      "type": "Event"
    },
    {
      "id": 3,
      "name": "Mary had a little lamb",
      "alias": "",
      "type": "Event",
      "tooltip": "Had means possessed not gave birth to"
    },
    {
      "id": 4,
      "name": "Mary's mum",
      "alias": "",
      "type": "Unresolved",
      "candidates": [
        "Thing",
        "Concept"
      ]
    },
    {
      "id": 5,
      "name": "Nursery rhyme",
      "alias": "",
      "type": "Unresolved",
      "candidates": [
        "Thing",
        "Concept"
      ]
    },
    {
      "id": 6,
      "name": "The lamb was sure to go",
      "alias": "",
      "type": "Event",
      "tooltip": "SatNav invented later"
    },
    {
      "id": 7,
      "name": "Whose fleece was white as snow",
      "alias": "",
      "type": "Event"
    }
  ],
  "edges": [
    {
      "id": 0,
      "source": 4,
      "target": 3,
      "dir": "",
      "tooltip": "wrote",
      "sstLinkType": "Expresses",
      "semOrigin": ""
    },
    {
      "id": 0,
      "source": 5,
      "target": 3,
      "dir": "",
      "tooltip": "has example",
      "sstLinkType": "Expresses",
      "semOrigin": ""
    },
    {
      "id": 0,
      "source": 3,
      "target": 7,
      "dir": "",
      "tooltip": "then followed by",
      "sstLinkType": "LeadsTo",
      "semOrigin": ""
    },
    {
      "id": 0,
      "source": 7,
      "target": 2,
      "dir": "",
      "tooltip": "then followed by",
      "sstLinkType": "LeadsTo",
      "semOrigin": ""
    },
    {
      "id": 0,
      "source": 2,
      "target": 6,
      "dir": "",
      "tooltip": "then followed by",
      "sstLinkType": "LeadsTo",
      "semOrigin": ""
    },
    {
      "id": 0,
      "source": 6,
      "target": 1,
      "dir": "",
      "tooltip": "then followed by",
      "sstLinkType": "LeadsTo",
      "semOrigin": ""
    },
    {
      "id": 0,
      "source": 1,
      "target": 3,
      "dir": "",
      "tooltip": "then followed by",
      "sstLinkType": "LeadsTo",
      "semOrigin": ""
    }
  ]
}
